README.rst
setup.py
drawtree/__init__.py
drawtree/drawtree.py
drawtree.egg-info/PKG-INFO
drawtree.egg-info/SOURCES.txt
drawtree.egg-info/dependency_links.txt
drawtree.egg-info/top_level.txt