Metadata-Version: 1.1
Name: drawtree
Version: 0.1.2
Summary: Draw binary tree in plain text
Home-page: https://github.com/msbanik/drawtree.git
Author: Madhusudan Banik
Author-email: msbanik@gmail.com
License: MIT
Keywords: tree draw ascii
Platform: UNKNOWN
Classifier: Development Status :: 2 - Pre-Alpha
Classifier: Programming Language :: Python
Classifier: Programming Language :: Python :: 2
Classifier: Programming Language :: Python :: 2.7
Classifier: Programming Language :: Python :: 3
Classifier: Programming Language :: Python :: 3.4
